irouter/__init__.py
irouter/base.py
irouter/call.py
irouter/chat.py
irouter/tool.py
irouter-0.3.0.dist-info/licenses/LICENSE
irouter-0.3.0.dist-info/METADATA
irouter-0.3.0.dist-info/WHEEL
irouter-0.3.0.dist-info/top_level.txt
irouter-0.3.0.dist-info/RECORD
