Metadata-Version: 2.4
Name: irouter
Version: 0.3.0
Summary: Easy access to 100s of LLMs with a few lines of code (using Openrouter).
Author-email: Carlo Lepelaars <info@carlolepelaars.nl>
License: MIT License
Requires-Python: <4,>=3.10
License-File: LICENSE
Requires-Dist: fastcore>=1.8.7
Requires-Dist: openai>=1.99.1
Provides-Extra: dev
Requires-Dist: ruff>=0.12.7; extra == "dev"
Requires-Dist: mkdocs>=1.4.2; extra == "dev"
Requires-Dist: python-dotenv>=1.1.1; extra == "dev"
Requires-Dist: mkdocs-material>=8.5.11; extra == "dev"
Requires-Dist: mkdocstrings-python>=1.7.1; extra == "dev"
Requires-Dist: pytest>=7.2.0; extra == "dev"
Requires-Dist: griffe>=0.36.4; extra == "dev"
Requires-Dist: ipython>=8.37.0; extra == "dev"
Dynamic: license-file
